[{"id":1,"nombre":"Procesador AMD Ryzen 3 4100 ","precio":20250,"marca":"amd","imagen":"/imagenes/ryzen34100.jpg","modelo":"4100","socket":"AM4 ryzen 4th Gen","nucleos":"4","frecuencia":"3800 Mhz","GPU":"NO posee graficos integrados","Hilos":"8","frecuenciaTurbo":"4000Mhz","familia":"AMD Ryzen 23","categoria":"procesador","stock":"3"},
{"id":2,"nombre":"Procesador AMD Ryzen 3 3200G ","precio":28500,"marca":"amd","imagen":"/imagenes/amd_ryzen_3_3200g.jpg","modelo":"3200G","socket":"AM4 APU 2th Gen","nucleos":"4","frecuencia":"3600 Mhz","GPU":"Radeon Vega 8","Hilos":"4","frecuenciaTurbo":"4000 mhz","familia":"AMD RYZEN 3","categoria":"procesador","stock":"4"},
{"id":3,"nombre":"Procesador AMD Ryzen 5 4500 ","precio":33550,"marca":"amd","imagen":"/imagenes/ryzen54500.jpg","modelo":"4500","socket":"AM4 APU 3th Gen","nucleos":"6","frecuencia":"3600 Mhz","GPU":"NO Posee Gráficos Integrados","Hilos":"12","frecuenciaTurbo":"4100 Mhz","familia":"AMD RYZEN 5","categoria":"procesador","stock":"2"},
{"id":4,"nombre":"Procesador AMD RYZEN 5 3600  ","precio":36750,"marca":"amd","imagen":"/imagenes/ryzen53600.jpg","modelo":"3600","socket":"AM4 Ryzen 3th Gen","nucleos":"6","frecuencia":"3600 Mhz","GPU":"NO Posee Gráficos Integrados","Hilos":"12","frecuenciaTurbo":"4200 Mhz","familia":"AMD RYZEN 5","categoria":"procesador","stock":"7"},
{"id":5,"nombre":"Procesador AMD RYZEN 3 3200G","precio":37750,"marca":"amd","imagen":"/imagenes/ryzen33200g.jpg","modelo":"3200G","socket":"AM4 APU 2th Gen","nucleos":"4","frecuencia":"3600 Mhz","GPU":"Radeon Vega 8","Hilos":"4","frecuenciaTurbo":"4000 Mhz","familia":"AMD RYZEN 3","categoria":"procesador","stock":"4"},
{"id":6,"nombre":"Procesador AMD Ryzen 5 PRO 4650G","precio":42400,"marca":"amd","imagen":"/imagenes/ryzen5pro4650g.jpg","modelo":"4650G","socket":"AM4 APU 3th Gen","nucleos":"6","frecuencia":"3700 Mhz","GPU":"Radeon Vega 7","Hilos":"12","frecuenciaTurbo":"4200 Mhz","familia":"AMD RYZEN 5","categoria":"procesador","stock":"8"},
{"id":7,"nombre":"Procesador AMD Ryzen 5 5600G","precio":56900,"marca":"amd","imagen":"/imagenes/ryzen5560g.jpg","modelo":"5600G","socket":"AM4 APU 5000","nucleos":"6","frecuencia":"3900 Mhz","GPU":"Radeon Vega 7","Hilos":"12","frecuenciaTurbo":"4400 Mhz","familia":"AMD RYZEN 5","categoria":"procesador","stock":"4"},
{"id":8,"nombre":"Procesador Intel Celeron G4900","precio":9920,"marca":"intel","imagen":"/imagenes/intelg4900.jpg","modelo":"4900G","socket":"1151 Coffe Lake","nucleos":"2","frecuencia":"3100 Mhz","GPU":"Intel UHD Graphics 610","Hilos":"2","frecuenciaTurbo":"3100 Mhz","familia":"Intel Celeron","categoria":"procesador","stock":"9"},
{"id":9,"nombre":"Procesador Intel Core i3 10100","precio":31500,"marca":"intel","imagen":"/imagenes/intelcorei310100.jpg","modelo":"10100","socket":"1200 Comet Lake","nucleos":"4","frecuencia":"3600 Mhz","GPU":"Intel HD Graphics 630","Hilos":"8","frecuenciaTurbo":"4300 Mhz","familia":"Intel Core i3","categoria":"procesador","stock":"2"},
{"id":10,"nombre":"Procesador Intel Core i5 10400F","precio":37600,"marca":"intel","imagen":"/imagenes/intelcorei510400f.jpg","modelo":"10400F","socket":"1200 Comet Lake","nucleos":"6","frecuencia":"2900 Mhz","GPU":"NO Posee Gráficos Integrados","Hilos":"12","frecuenciaTurbo":"4300 Mhz","familia":"Intel Core i5","categoria":"procesador","stock":"5"},
{"id":11,"nombre":"Procesador Intel Core i7 10700F","precio":77900,"marca":"intel","imagen":"/imagenes/intelcorei710700f.jpg","modelo":"10700F","socket":"1200 Comet Lake","nucleos":"8","frecuencia":"2900 Mhz","GPU":"NO Posee Gráficos Integrados","Hilos":"16","frecuenciaTurbo":"4800 Mhz","familia":"Intel Core i7","categoria":"procesador","stock":"3"},
{"id":12,"nombre":"Procesador Intel Core i7 10700","precio":89500,"marca":"intel","imagen":"/imagenes/intelcorei71070048ghz.jpg","modelo":"10700","socket":"1200 Comet Lake","nucleos":"8","frecuencia":"2900 Mhz","GPU":"Intel HD Graphics 630","Hilos":"17","frecuenciaTurbo":"4800 Mhz","familia":"Intel Core i7","categoria":"procesador","stock":"8"},
{"id":13,"nombre":"Procesador Intel Core i5 9500","precio":47600,"marca":"intel","imagen":"/imagenes/intecorei595009th.jpg","modelo":"9500","socket":"1151 Coffe Lake","nucleos":"6","frecuencia":"3000 Mhz","GPU":"Intel UHD Graphics 630","Hilos":"6","frecuenciaTurbo":"4400 Mhz","familia":"Intel Core i5","categoria":"procesador","stock":"4"},
{"id":14,"nombre":"Procesador Intel Core i9 12900F","precio":157000,"marca":"intel","imagen":"/imagenes/intelcorei912900f.jpg","modelo":"12900F","socket":"--","nucleos":"10","frecuencia":"28000Mhz","GPU":"NO Posee Gráficos Integrados","Hilos":"--","frecuenciaTurbo":"5200 Mhz","familia":"Intel Core i9","categoria":"procesador","stock":"8"},
{"id":15,"nombre":"Placa de Video Asrock RX 570","precio":71550,"marca":"amd","tipo":"pcie","chipset":"RX 570","entrada":"No","caracteristicas":"-","vga":"0","hdmi":"1","displayports":"3","imagen":"/imagenes/RX570.jpg","categoria":"grafica","stock":"4"},
{"id":16,"nombre":"Placa de Video XFX Radeon RX 6500 XT","precio":71750,"marca":"amd","tipo":"pcie","chipset":"RX 6500 XT","entrada":"no","caracteristicas":"Ray Tracing","vga":"0","hdmi":"1","displayports":"1","imagen":"/imagenes/RX6500XT.jpg","categoria":"grafica","stock":"9"},
{"id":17,"nombre":"Placa de Video XFX Radeon RX 570","precio":72700,"marca":"amd","tipo":"pcie","chipset":"RX 570","entrada":"No","caracteristicas":"-","vga":"0","hdmi":"1","displayports":"3","imagen":"/imagenes/XFXradeonRX570.jpg","categoria":"tarjeta grafica","stock":"2"},
{"id":18,"nombre":"Placa de Video Radeon RX 6600","precio":99900,"marca":"amd","tipo":"pcie","chipset":"RX 6600","entrada":"No","caracteristicas":"Ray Tracing","vga":"0","hdmi":"1","displayports":"3","imagen":"/imagenes/RX6600.jpg","categoria":"grafica","stock":"7"},
{"id":19,"nombre":"Placa de Video XFX Radeon RX 6600","precio":100050,"marca":"amd","tipo":"pcie","chipset":"RX 6600 XT","entrada":"no","caracteristicas":"Ray Tracing","vga":"0","hdmi":"1","displayports":"3","imagen":"/imagenes/XFXradeonRX6600.jpg","categoria":"grafica","stock":"4"},
{"id":20,"nombre":"Placa de Video XFX Radeon RX 6600 XT","precio":117000,"marca":"amd","tipo":"pcie","chipset":"RX 6600 XT","entrada":"no","caracteristicas":"Ray Tracing","vga":"0","hdmi":"1","displayports":"3","imagen":"/imagenes/radeonRC6600XT.jpg","categoria":"grafica","stock":"5"},
{"id":21,"nombre":"Placa de Video Asrock Radeon RX 6700 XT","precio":138100,"marca":"amd","tipo":"pcie","chipset":"RX 6700 XT","entrada":"no","caracteristicas":"Ray Tracing","vga":"0","hdmi":"1","displayports":"3","imagen":"/imagenes/RX6700XT.jpg","categoria":"grafica","stock":"3"},
{"id":22,"nombre":"Placa de Video GALAX GeForce RTX 3050","precio":124950,"marca":"geforce","tipo":"pcie","chipset":"RTX 3050","entrada":"no","caracteristicas":"Ray Tracing + DLSS","vga":"0","hdmi":"1","displayports":"3","imagen":"/imagenes/RTX3050.jpg","categoria":"grafica","stock":"6"},
{"id":23,"nombre":"Placa de Video Zotac GeForce RTX 3070 Ti ","precio":214550,"marca":"geforce","tipo":"pcie","chipset":"RTX 3070 Ti","entrada":"no","caracteristicas":"Ray Tracing + DLSS","vga":"0","hdmi":"1","displayports":"3","imagen":"/imagenes/RTX3070Ti.jpg","categoria":"grafica","stock":"4"},
{"id":24,"nombre":"laca de Video GALAX GeForce RTX 3080 8gb","precio":243750,"marca":"geforce","tipo":"pcie","chipset":"RTX 3080","entrada":"no","caracteristicas":"Ray Tracing + DLSS","vga":"0","hdmi":"1","displayports":"3","imagen":"/imagenes/RTX3080.jpg","categoria":"grafica","stock":"2"},
{"id":25,"nombre":"Placa de Video GALAX GeForce RTX 3080 12gb","precio":257700,"marca":"geforce","tipo":"pcie","chipset":"RTX 3080","entrada":"no","caracteristicas":"Ray Tracing + DLSS","vga":"0","hdmi":"1","displayports":"3","imagen":"/imagenes/RTX308012GB.jpg","categoria":"grafica","stock":"6"},
{"id":26,"nombre":"Placa de Video GALAX GeForce RTX 3080 Ti","precio":303100,"marca":"geforce","tipo":"pcie","chipset":"RTX 3080 Ti","entrada":"no","caracteristicas":"Ray Tracing + DLSS","vga":"0","hdmi":"1","displayports":"3","imagen":"/imagenes/RTX3080Ti.jpg","categoria":"grafica","stock":"4"},
{"id":27,"nombre":"Placa de Video MSI GeForce RTX 3090 24gb","precio":350500,"marca":"geforce","tipo":"pcie","chipset":"RTX 3090","entrada":"no","caracteristicas":"Ray Tracing + DLSS","vga":"0","hdmi":"1","displayports":"3","imagen":"/imagenes/RTX3090.jpg","categoria":"grafica","stock":"2"},
{"id":28,"nombre":"Placa de Video Zotac GeForce RTX 3090","precio":345000,"marca":"geforce","tipo":"pcie","chipset":"RTX 3090","entrada":"no","caracteristicas":"Ray Tracing + DLSS","vga":"0","hdmi":"1","displayports":"3","imagen":"/imagenes/zotacRTX3090.jpg","categoria":"grafica","stock":"8"},
{"id":29,"nombre":"Memoria GeiL DDR4 16GB 3000MHz","precio":41500,"marca":"geil","capacidad":"16 gb","velocidad":"3000 mhz","tipo":"DDR4","cantidad":"1","latencia":"16 cl","voltaje":"1.35 v","disparador":"Si","disparadoral":"Si","imagen":"/imagenes/geilDDR416GB.jpg","categoria":"memoria","stock":"6"},
{"id":30,"nombre":"Memoria GeiL DDR4 16GB 3000MHz Orion","precio":34650,"marca":"geil","capacidad":"8 gb","velocidad":"3000 mhz","tipo":"DDR4","cantidad":"1","latencia":"16 cl","voltaje":"1.35 v","disparador":"si","disparadoral":"no","imagen":"/imagenes/geilorionDDR416gb.jpg","categoria":"memoria","stock":"5"},
{"id":31,"nombre":"Memoria GeiL DDR4 16GB 3000MHz Orion","precio":34650,"marca":"geil","capacidad":"16 gb","velocidad":"3000 mhz","tipo":"DDR4","cantidad":"1","latencia":"16 cl","voltaje":"1.35 v","disparador":"si","disparadoral":"no","imagen":"/imagenes/geilorionDDR416gbblack.jpg","categoria":"memoria","stock":"8"},
{"id":32,"nombre":"Memoria Adata DDR4 4GB 2666MHz Value","precio":9300,"marca":"adata","capacidad":"4 gb","velocidad":"2666 mhz","tipo":"DDR4","cantidad":"1","latencia":"22 cl","voltaje":"1.20 v","disparador":"no","disparadoral":"no","imagen":"/imagenes/adataDDR44GB.jpg","categoria":"memoria","stock":"9"},
{"id":33,"nombre":"Memoria Team DDR4 8GB 2666MHz T-Force Gray","precio":18920,"marca":"vulcan","capacidad":"8 gb","velocidad":"2666 mhz","tipo":"DDR4","cantidad":"1","latencia":"18 cl","voltaje":"1.20 v","disparador":"si","disparadoral":"no","imagen":"/imagenes/vulcanDDR48GB.jpg","categoria":"memoria","stock":"4"},
{"id":34,"nombre":"Memoria Team DDR4 8GB 2666MHz T-Force","precio":18290,"marca":"vulcan","capacidad":"8 gb","velocidad":"2666 mhz","tipo":"DDR4","cantidad":"1","latencia":"18 cl","voltaje":"1.20 v","disparador":"si","disparadoral":"no","imagen":"/imagenes/vulcanDDR48GBred.jpg","categoria":"memoria","stock":"2"},
{"id":35,"nombre":"Memoria Team DDR4 8GB 3000MHz","precio":20450,"marca":"vulcan","capacidad":"8 gb","velocidad":"3000 mhz","tipo":"DDR4","cantidad":"1","latencia":"16 cl","voltaje":"1.35 v","disparador":"si","isparadoral":"no","imagen":"/imagenes/vulcanDDR48GB3000MHz.jpg","categoria":"memoria","stock":"4"},
{"id":36,"nombre":"Memoria Team DDR4 8GB 3200MHz","precio":18650,"marca":"vulcan","capacidad":"8 gb","velocidad":"3200 mhz","tipo":"DDR4","cantidad":"1","latencia":"16 cl","voltaje":"1.35 v","disparador":"si","disparadoral":"no","imagen":"/imagenes/vulcanDDR48GB3200MHz.jpg","categoria":"memoria","stock":"3"},
{"id":37,"nombre":"Memoria GeiL DDR4 16GB 3000MHZ","precio":33900,"marca":"geil","capacidad":"16 gb","velocidad":"3000 mhz","tipo":"DDR4","cantidad":"1","latencia":"16 cl","voltaje":"1.35 v","disparador":"si","disparadoral":"si","imagen":"/imagenes/geilDDR416GB3000MHz.jpg","categoria":"memoria","stock":"6"},
{"id":38,"nombre":"Memoria Patriot Viper DDR4 8GB 3200MHz Steel","precio":20450,"marca":"viper","capacidad":"8 gb","velocidad":"3200 mhz","tipo":"DDR4","cantidad":"1","latencia":"16 cl","voltaje":"1.35 v","disparador":"no","disparadoral":"si","imagen":"/imagenes/viperDDR48GB3200MHz.jpg","categoria":"memoria","stock":"2"},
{"id":39,"nombre":"Memoria Adata DDR4 8GB 3200MHz XPG","precio":21350,"marca":"adata","capacidad":"8 gb","velocidad":"3200 mhz","tipo":"DDR4","cantidad":"1","latencia":"16 cl","voltaje":"1.20 v","disparador":"si","disparadoral":"no","imagen":"/imagenes/adataDDR44GB3200MHz.jpg","categoria":"memoria","stock":"4"},
{"id":40,"nombre":"Memoria OLOy DDR4 16GB 3000MHz ","precio":36200,"marca":"oloy","capacidad":"16 gb","velocidad":"3000 mhz","tipo":"DDR4","cantidad":"1","latencia":"16 cl","voltaje":"1.35 v","disparador":"si","disparadoral":"si","imagen":"/imagenes/oloyDDR43000MH.jpg.jpg","categoria":"memoria","stock":"7"},
{"id":41,"nombre":"Memoria OLOy DDR4 16GB Warhawk Black 3000MHz","precio":40500,"marca":"oloy","capacidad":"16 gb","velocidad":"3000 mhz","tipo":"DDR4","cantidad":"1","latencia":"16 cl","voltaje":"1.35 v","disparador":"si","disparadoral":"si","imagen":"/imagenes/oloyDDR416Gb3000MHz.jpg","categoria":"memoria","stock":"4"},
{"id":42,"nombre":"Memoria Team DDR4 8GB 3200MHz T-Force","precio":19800,"marca":"vulcan","capacidad":"8 gb","velocidad":"3200 mhz","tipo":"DDR4","cantidad":"1","latencia":"16 cl","voltaje":"1.35 v","disparador":"si","disparadoral":"si","imagen":"/imagenes/teamDDR43200MHz.jpg","categoria":"memoria","stock":"7"},
{"id":43,"nombre":"Fuente ASUS ROG THOR 850W 80 Plus","precio":69350,"marca":"asus","watts":"850 w","wattsr":"852 w","formato":"ATX","compatible":"Si","certificacion":"80 PLUS Platinum","modoh":"Si","tipo":"Full Modular","ampers":"71 a","fuente":"Si","color":"Negro","iluminacion":"RGB","imagen":"/imagenes/asusROG850w.jpg","categoria":"fuente","stock":6},
{"id":57,"nombre":"Mother ASUS PRIME A320M-K AM4","precio":16800,"marca":"asus","slotPcie16X":"1","slotPcie1X":"2","tecnología":"-","puertos":"4","vga":"1","hdmi":"1","memoria":"DDR4","cantidadMemorias":"2","placaWifi":"No","placaDeRed":"1 Gb/s","usb20":"2","usb30":"0","usb31":"4","usb32":"0","usbC":"0","watts":"140","consumo":"45 w","imagen":"/imagenes/asusprimeA320M-KAM4.jpg","categoria":"mother","stock":1},
{"id":71,"nombre":"Gabinete Lian Li Lancool 205 Black 2x120mm","precio":22000,"marca":"lianli","factor":"ITX,M-ATX,ATX","fuente":"no","ventana":"si","tipoVentana":"Vidrio templado","color":"negro","alto":"485 mm","ancho":"205 mm","profundidad":"415 mm","tipoFuente":"ATX","imagen":"/imagenes/lianli-lancool-205.jpg","categoria":"gabinete","stock":8}]  